{
  "metadata": {
    "test_name": "Task 4.4 Optimized Vector Store Test",
    "timestamp": "20250923_221638",
    "test_type": "optimized_vector_store_performance"
  },
  "hnsw_index_tests": {},
  "bulk_insert_tests": {},
  "search_performance_tests": {},
  "optimization_analysis": {},
  "overall_status": "FAILED",
  "error_message": "테스트 실행 중 예외 발생: cannot access local variable 'index_config' where it is not associated with a value",
  "performance_metrics": {
    "index_creation_time": 0.5,
    "bulk_insert_throughput": 0.0,
    "search_performance": 0.0,
    "memory_efficiency": 0.0
  }
}